geodaisy/__init__.py
geodaisy/converters.py
geodaisy/geo_object.py
geodaisy-0.1.1.dist-info/DESCRIPTION.rst
geodaisy-0.1.1.dist-info/METADATA
geodaisy-0.1.1.dist-info/RECORD
geodaisy-0.1.1.dist-info/WHEEL
geodaisy-0.1.1.dist-info/metadata.json
geodaisy-0.1.1.dist-info/top_level.txt
